cmrsim/__init__.py
cmrsim/analytic/__init__.py
cmrsim/analytic/_composite_signal.py
cmrsim/analytic/simulation.py
cmrsim/analytic/contrast/__init__.py
cmrsim/analytic/contrast/_spatial.py
cmrsim/analytic/contrast/base.py
cmrsim/analytic/contrast/coil_sensitivities.py
cmrsim/analytic/contrast/diffusion_weighting.py
cmrsim/analytic/contrast/offresonance.py
cmrsim/analytic/contrast/phase_tracking.py
cmrsim/analytic/contrast/sequences.py
cmrsim/analytic/contrast/t2_star.py
cmrsim/analytic/encoding/__init__.py
cmrsim/analytic/encoding/_from_sequence.py
cmrsim/analytic/encoding/base.py
cmrsim/analytic/encoding/cartesian.py
cmrsim/bloch/__init__.py
cmrsim/bloch/_base.py
cmrsim/bloch/_generic.py
cmrsim/bloch/_ideal.py
cmrsim/bloch/_multi_coil.py
cmrsim/bloch/submodules.py
cmrsim/datasets/__init__.py
cmrsim/datasets/_analytic.py
cmrsim/datasets/_base.py
cmrsim/datasets/_bloch.py
cmrsim/datasets/_cardiac_mesh.py
cmrsim/datasets/_flow.py
cmrsim/datasets/_regular_grid.py
cmrsim/reconstruction/__init__.py
cmrsim/reconstruction/base.py
cmrsim/reconstruction/cartesian.py
cmrsim/simulation_templates/__init__.py
cmrsim/simulation_templates/experimental_optimization.py
cmrsim/simulation_templates/flow.py
cmrsim/trajectory/__init__.py
cmrsim/trajectory/_base.py
cmrsim/trajectory/_breathing.py
cmrsim/trajectory/_diffusion.py
cmrsim/trajectory/_flow.py
cmrsim/trajectory/_proper_ortho_decomp.py
cmrsim/trajectory/_taylor.py
cmrsim/utils/__init__.py
cmrsim/utils/coordinates.py
cmrsim/utils/display.py
cmrsim/utils/eddy_current.py
cmrsim/utils/particle_properties.py
cmrsim/utils/snr.py
cmrsim-0.31.dist-info/LICENSE
cmrsim-0.31.dist-info/METADATA
cmrsim-0.31.dist-info/WHEEL
cmrsim-0.31.dist-info/top_level.txt
cmrsim-0.31.dist-info/RECORD
