Metadata-Version: 2.1
Name: cmrsim
Version: 0.31
Home-page: https://gitlab.ethz.ch//ibt-cmr/mri_simulation/cmrsim/
Author: Jonathan Weine, Charles McGrath
Project-URL: Documentation, https://people.ee.ethz.ch/~jweine/cmrsim/latest/index.html
Project-URL: Source, https://gitlab.ethz.ch//ibt-cmr/mri_simulation/cmrsim/
Project-URL: Institute, https://cmr.ethz.ch/
Requires-Python: >=3.6
License-File: LICENSE
Requires-Dist: tensorflow ==2.15.1
Requires-Dist: pyvista >=0.42
Requires-Dist: numpy >=1.22
Requires-Dist: pint >=0.18
Requires-Dist: cmrseq >=0.23
Provides-Extra: cuda
Requires-Dist: tensorflow[and-cuda] ==2.15.1 ; extra == 'cuda'
